pymosa/__init__.py
pymosa/m26.py
pymosa/m26.yaml
pymosa/m26_configuration.yaml
pymosa/m26_raw_data.py
pymosa/m26_readout.py
pymosa/noise_occupancy_scan.py
pymosa/noise_tuning.py
pymosa/online.py
pymosa/plotting.py
pymosa/tune_tlu.py
pymosa/firmware/mmc3_m26_eth.bin
pymosa/firmware/mmc3_m26_eth.bit
pymosa/m26_config/m26_threshold_10.yaml
pymosa/m26_config/m26_threshold_11.yaml
pymosa/m26_config/m26_threshold_4.yaml
pymosa/m26_config/m26_threshold_5.yaml
pymosa/m26_config/m26_threshold_6.yaml
pymosa/m26_config/m26_threshold_7.yaml
pymosa/m26_config/m26_threshold_8.yaml
pymosa/m26_config/m26_threshold_9.yaml
pymosa/online_monitor/__init__.py
pymosa/online_monitor/hit_correlator_converter.py
pymosa/online_monitor/hit_correlator_receiver.py
pymosa/online_monitor/pymosa_converter.py
pymosa/online_monitor/pymosa_histogrammer.py
pymosa/online_monitor/pymosa_producer_sim.py
pymosa/online_monitor/pymosa_receiver.py
pymosa/online_monitor/pymosa_sender.py
pymosa/online_monitor/start_pymosa_online_monitor.py
pymosa-1.0.0.dist-info/LICENSE
pymosa-1.0.0.dist-info/METADATA
pymosa-1.0.0.dist-info/WHEEL
pymosa-1.0.0.dist-info/entry_points.txt
pymosa-1.0.0.dist-info/top_level.txt
pymosa-1.0.0.dist-info/RECORD
